flask_api_sqlalchemy/__init__.py
flask_api_sqlalchemy/api.py
flask_api_sqlalchemy/cli.py
flask_api_sqlalchemy/exceptions.py
flask_api_sqlalchemy-0.1.6.dist-info/AUTHORS.md
flask_api_sqlalchemy-0.1.6.dist-info/LICENSE
flask_api_sqlalchemy-0.1.6.dist-info/METADATA
flask_api_sqlalchemy-0.1.6.dist-info/WHEEL
flask_api_sqlalchemy-0.1.6.dist-info/RECORD
