Metadata-Version: 2.3
Name: flask-api-sqlalchemy
Version: 0.1.6
Summary: Flask extension for automatically generating RESTful APIs from SQLAlchemy models
License: MIT
Keywords: flask,sqlalchemy,api,restful
Author: Sean McCarthy
Author-email: sean.mccarthy@hotmail.com
Requires-Python: >=3.9,<4.0
Classifier: License :: OSI Approved :: MIT License
Classifier: Programming Language :: Python :: 3
Classifier: Programming Language :: Python :: 3.9
Classifier: Programming Language :: Python :: 3.10
Classifier: Programming Language :: Python :: 3.11
Classifier: Programming Language :: Python :: 3.12
Classifier: Programming Language :: Python :: 3.13
Requires-Dist: flask (>=2.0.0)
Requires-Dist: flask-restx (>=1.3.0,<2.0.0)
Requires-Dist: flask-sqlalchemy (>=3.1.1,<4.0.0)
Requires-Dist: inflection (>=0.5.1,<0.6.0)
Requires-Dist: marshmallow (>=3.0.0,<4.0.0)
Project-URL: Documentation, https://mccarthysean.dev/flask-api-sqlalchemy
Project-URL: Homepage, https://mccarthysean.dev/flask-api-sqlalchemy
Project-URL: Repository, https://github.com/mccarthysean/flask-api-sqlalchemy
